tz_canary/__init__.py
tz_canary/exceptions.py
tz_canary/infer.py
tz_canary/transitions_data.py
tz_canary/validate.py
tz_canary-0.2.0.dist-info/LICENSE
tz_canary-0.2.0.dist-info/METADATA
tz_canary-0.2.0.dist-info/WHEEL
tz_canary-0.2.0.dist-info/RECORD
