Metadata-Version: 2.1
Name: tz-canary
Version: 0.2.0
Summary: Infer plausible time zones for a time series dataset based on Daylight Savings Time switches
Home-page: https://github.com/leonoverweel/tz-canary
License: MIT
Author: Leon Overweel
Author-email: l.overweel@gmail.com
Requires-Python: >=3.9,<4.0
Classifier: License :: OSI Approved :: MIT License
Classifier: Programming Language :: Python :: 3
Classifier: Programming Language :: Python :: 3.9
Classifier: Programming Language :: Python :: 3.10
Classifier: Programming Language :: Python :: 3.11
Classifier: Programming Language :: Python :: 3.12
Requires-Dist: pandas (>=2.0.3,<3.0.0)
Requires-Dist: pytz (>=2023.3,<2023.4)
Project-URL: Repository, https://github.com/leonoverweel/tz-canary
